shcaicli/__init__.py
shcaicli/api.py
shcaicli/shcai_exc.py
shcaicli-0.0.8.dist-info/LICENSE
shcaicli-0.0.8.dist-info/METADATA
shcaicli-0.0.8.dist-info/WHEEL
shcaicli-0.0.8.dist-info/top_level.txt
shcaicli-0.0.8.dist-info/RECORD
