Metadata-Version: 2.1
Name: shcaicli
Version: 0.0.8
Summary: SHC.Ai Cli
Home-page: https://www.ihealthgroup.com.br
Author: iHealth Group
Author-email: rafael.morais@ihealthgroup.com.br
Project-URL: Bug Tracker, https://github.com/ihealth-group/shcai-cli/issues
Classifier: Programming Language :: Python :: 3
Requires-Python: >=3.8
License-File: LICENSE
Requires-Dist: requests ==2.31.0
